arweave/__init__.py
arweave/arweave_lib.py
arweave/deep_hash.py
arweave/file_io.py
arweave/merkle.py
arweave/transaction_uploader.py
arweave/utils.py
arweave_python_client-1.0.17.dev0.dist-info/LICENSE
arweave_python_client-1.0.17.dev0.dist-info/METADATA
arweave_python_client-1.0.17.dev0.dist-info/WHEEL
arweave_python_client-1.0.17.dev0.dist-info/top_level.txt
arweave_python_client-1.0.17.dev0.dist-info/RECORD
